django_redis_task_lock/__init__.py
django_redis_task_lock-0.7.dist-info/LICENSE
django_redis_task_lock-0.7.dist-info/METADATA
django_redis_task_lock-0.7.dist-info/WHEEL
django_redis_task_lock-0.7.dist-info/top_level.txt
django_redis_task_lock-0.7.dist-info/RECORD
