Metadata-Version: 2.1
Name: django-redis-task-lock
Version: 0.7
Summary: Redis task lock decorator for django celery tasks
Home-page: https://github.com/Lenders-Cooperative/django-redis-task-lock
Author: Levi Anderson
Classifier: Programming Language :: Python :: 3
Classifier: License :: OSI Approved :: BSD License
Classifier: Operating System :: OS Independent
Requires-Python: >=3.6
License-File: LICENSE
Requires-Dist: django >=2.2.9
